topsis/__init__.py
topsis/topsis.py
topsis2-0.0.2.dist-info/LICENSE
topsis2-0.0.2.dist-info/METADATA
topsis2-0.0.2.dist-info/WHEEL
topsis2-0.0.2.dist-info/top_level.txt
topsis2-0.0.2.dist-info/RECORD
