Metadata-Version: 2.1
Name: topsis2
Version: 0.0.2
Summary: TOPSIS
Home-page: UNKNOWN
Author: seyedsaman (sam) emami
Author-email: <github@samanemami.com>
License: UNKNOWN
Keywords: python,topsis,mcdm,madm
Platform: UNKNOWN
Classifier: Development Status :: 1 - Planning
Classifier: Intended Audience :: Developers
Classifier: Programming Language :: Python :: 3
Classifier: Operating System :: Unix
Classifier: Operating System :: MacOS :: MacOS X
Classifier: Operating System :: Microsoft :: Windows
License-File: LICENSE
Requires-Dist: pandas
Requires-Dist: numpy
Requires-Dist: scipy
